ragorez/__init__.py
ragorez/rag/__init__.py
ragorez/rag/pipeline.py
ragorez/rag/graph/__init__.py
ragorez/rag/graph/db.py
ragorez/rag/graph/knowledge_extraction.py
ragorez/rag/graph/llm_based_knowledge_extractor.py
ragorez/rag/graph/model.py
ragorez/rag/graph/neo4j.py
ragorez/rag/llm/__init__.py
ragorez/rag/llm/hugging_face.py
ragorez/rag/llm/llm_provider.py
ragorez/rag/llm/openrouter.py
ragorez/rag/vector/__init__.py
ragorez/rag/vector/chromadb.py
ragorez/rag/vector/db.py
ragorez_rag-0.1.5.dist-info/METADATA
ragorez_rag-0.1.5.dist-info/WHEEL
ragorez_rag-0.1.5.dist-info/top_level.txt
ragorez_rag-0.1.5.dist-info/RECORD
