Metadata-Version: 2.4
Name: ragorez-rag
Version: 0.1.5
Summary: Rag
Author-email: Roman Stepanov <ya.barrymor@yandex.ru>
License: MIT
Project-URL: Homepage, https://github.com/haleen24/piki_tan
Project-URL: Repository, https://github.com/haleen24/piki_tan
Classifier: Programming Language :: Python :: 3
Classifier: License :: OSI Approved :: MIT License
Requires-Python: >=3.12
Requires-Dist: ragorez-common>=0.2.2
